icepack/__init__.py
icepack/cli.py
icepack/error.py
icepack/helper.py
icepack/meta.py
icepack/model.py
icepack-1.1.0.dist-info/LICENSE
icepack-1.1.0.dist-info/METADATA
icepack-1.1.0.dist-info/WHEEL
icepack-1.1.0.dist-info/entry_points.txt
icepack-1.1.0.dist-info/top_level.txt
icepack-1.1.0.dist-info/RECORD
