Metadata-Version: 2.1
Name: icepack
Version: 1.1.0
Summary: Encrypting File Archiver
Home-page: https://github.com/alxndr42/icepack
Author: Alexander Dietrich
Author-email: alexander@dietrich.cx
Classifier: Programming Language :: Python :: 3
Classifier: License :: OSI Approved :: GNU General Public License v3 or later (GPLv3+)
Requires-Python: >=3.8
License-File: LICENSE
Requires-Dist: click (~=8.0)
Requires-Dist: pydantic (~=1.9)
